README.txt
setup.cfg
setup.py
collective/__init__.py
collective.jaop.egg-info/PKG-INFO
collective.jaop.egg-info/SOURCES.txt
collective.jaop.egg-info/dependency_links.txt
collective.jaop.egg-info/entry_points.txt
collective.jaop.egg-info/namespace_packages.txt
collective.jaop.egg-info/not-zip-safe
collective.jaop.egg-info/requires.txt
collective.jaop.egg-info/top_level.txt
collective/jaop/HISTORY.txt
collective/jaop/INSTALL.txt
collective/jaop/README
collective/jaop/__init__.py
collective/jaop/configure.zcml
collective/jaop/version.txt
collective/jaop/browser/__init__.py
collective/jaop/browser/autodiscovery.pt
collective/jaop/browser/blank.pt
collective/jaop/browser/configure.zcml
collective/jaop/browser/description.pt
collective/jaop/browser/description.py
collective/jaop/browser/opensearch.png
collective/jaop/browser/opensearchprefs.py
collective/jaop/browser/rssview.pt
collective/jaop/browser/rssview.py
collective/jaop/browser/search.png
collective/jaop/browser/suggestion.pt
collective/jaop/browser/suggestion.py
collective/jaop/browser/viewlet.py
collective/jaop/locales/opensearch.pot
collective/jaop/locales/af/LC_MESSAGES/opensearch.mo
collective/jaop/locales/af/LC_MESSAGES/opensearch.po
collective/jaop/locales/ar/LC_MESSAGES/opensearch.mo
collective/jaop/locales/ar/LC_MESSAGES/opensearch.po
collective/jaop/locales/bn/LC_MESSAGES/opensearch.mo
collective/jaop/locales/bn/LC_MESSAGES/opensearch.po
collective/jaop/locales/ca/LC_MESSAGES/opensearch.mo
collective/jaop/locales/ca/LC_MESSAGES/opensearch.po
collective/jaop/locales/de/LC_MESSAGES/opensearch.mo
collective/jaop/locales/de/LC_MESSAGES/opensearch.po
collective/jaop/locales/en/LC_MESSAGES/opensearch.mo
collective/jaop/locales/en/LC_MESSAGES/opensearch.po
collective/jaop/locales/es/LC_MESSAGES/opensearch.mo
collective/jaop/locales/es/LC_MESSAGES/opensearch.po
collective/jaop/locales/fr/LC_MESSAGES/opensearch.mo
collective/jaop/locales/fr/LC_MESSAGES/opensearch.po
collective/jaop/locales/hi/LC_MESSAGES/opensearch.mo
collective/jaop/locales/hi/LC_MESSAGES/opensearch.po
collective/jaop/locales/hu/LC_MESSAGES/opensearch.mo
collective/jaop/locales/hu/LC_MESSAGES/opensearch.po
collective/jaop/locales/it/LC_MESSAGES/opensearch.mo
collective/jaop/locales/it/LC_MESSAGES/opensearch.po
