Metadata-Version: 1.0
Name: collective.jaop
Version: 1.2
Summary: This product implements OpenSearch interface in a PloneSite.
Home-page: http://plone.org/products/jaop-just-an-opensearch-product-1/
Author: Héctor José Rico García
Author-email: plone-developers@lists.sourceforge.net
License: GPL
Keywords: OpenSearch
Platform: UNKNOWN
Classifier: Framework :: Plone
Classifier: Programming Language :: Python
Classifier: Topic :: Software Development :: Libraries :: Python Modules
